zmqbus/__init__.py
zmqbus/bus.py
zmqbus/debug.py
zmqbus/device.py
zmqbus/py.typed
zmqbus-0.2.2b0.dist-info/LICENSE.txt
zmqbus-0.2.2b0.dist-info/WHEEL
zmqbus-0.2.2b0.dist-info/METADATA
zmqbus-0.2.2b0.dist-info/RECORD
