Metadata-Version: 2.1
Name: zmqbus
Version: 0.2.2b0
Summary: A data bus for ZeroMQ
Author-email: Flavio Veloso Soares <flaviovs@magnux.com>
Requires-Python: >=3.7
Classifier: License :: OSI Approved :: MIT License
Requires-Dist: pyzmq
Requires-Dist: codespell ; extra == "dev"
Requires-Dist: flake8-bugbear ; extra == "dev"
Requires-Dist: flake8-builtins ; extra == "dev"
Requires-Dist: flake8-docstrings ; extra == "dev"
Requires-Dist: flake8-tidy-imports ; extra == "dev"
Requires-Dist: flake8-walrus ; extra == "dev"
Requires-Dist: flake8 ; extra == "dev"
Requires-Dist: flit ; extra == "dev"
Requires-Dist: mypy ; extra == "dev"
Requires-Dist: pylint ; extra == "dev"
Requires-Dist: taskipy ; extra == "dev"
Project-URL: Home, https://github.com/flaviovs/zmqbus
Provides-Extra: dev
